odoo/addons/stock_reception_screen_measuring_device/README.rst
odoo/addons/stock_reception_screen_measuring_device/__init__.py
odoo/addons/stock_reception_screen_measuring_device/__manifest__.py
odoo/addons/stock_reception_screen_measuring_device/i18n/stock_reception_screen_measuring_device.pot
odoo/addons/stock_reception_screen_measuring_device/models/__init__.py
odoo/addons/stock_reception_screen_measuring_device/models/measuring_device.py
odoo/addons/stock_reception_screen_measuring_device/models/stock_reception_screen.py
odoo/addons/stock_reception_screen_measuring_device/readme/CONTRIBUTORS.rst
odoo/addons/stock_reception_screen_measuring_device/readme/DESCRIPTION.rst
odoo/addons/stock_reception_screen_measuring_device/readme/USAGE.rst
odoo/addons/stock_reception_screen_measuring_device/static/description/icon.png
odoo/addons/stock_reception_screen_measuring_device/static/description/index.html
odoo/addons/stock_reception_screen_measuring_device/views/measuring_device_view.xml
odoo/addons/stock_reception_screen_measuring_device/views/stock_reception_screen_view.xml
odoo13_addon_stock_reception_screen_measuring_device-13.0.1.0.1.dist-info/METADATA
odoo13_addon_stock_reception_screen_measuring_device-13.0.1.0.1.dist-info/WHEEL
odoo13_addon_stock_reception_screen_measuring_device-13.0.1.0.1.dist-info/top_level.txt
odoo13_addon_stock_reception_screen_measuring_device-13.0.1.0.1.dist-info/RECORD
