Metadata-Version: 2.1
Name: odoo13-addon-stock-reception-screen-measuring-device
Version: 13.0.1.0.1
Summary: Allow to use a measuring device from a reception screen.for packaging measurement
Home-page: https://github.com/OCA/wms
Author: Camptocamp, Odoo Community Association (OCA)
Author-email: support@odoo-community.org
License: AGPL-3
Platform: UNKNOWN
Classifier: Programming Language :: Python
Classifier: Framework :: Odoo
Classifier: License :: OSI Approved :: GNU Affero General Public License v3
Classifier: Development Status :: 3 - Alpha
Requires-Python: >=3.5
Requires-Dist: odoo13-addon-stock-measuring-device
Requires-Dist: odoo13-addon-stock-reception-screen
Requires-Dist: odoo (<13.1dev,>=13.0a)
